.DS_Store
UNISA-1.0.2.dist-info/RECORD
UNISA-1.0.2.dist-info/metadata.json
UNISA-1.0.2.dist-info/WHEEL
UNISA-1.0.2.dist-info/entry_points.txt
UNISA-1.0.2.dist-info/DESCRIPTION.rst
UNISA-1.0.2.dist-info/top_level.txt
UNISA-1.0.2.dist-info/METADATA
UNISA/UNISA.py
UNISA/__init__.py
UNISA/__main__.py
